{"status": "success", "message": "small nasdaq success, small nyse success, mid nasdaq success, mid nyse success", "change_pct": {"best3": [{"ticker": "NVA", "company": "Nova Minerals Limited ADR", "sector": "Basic Materials", "industry": "Other Industrial Metals & Mining", "market_cap": "481.33M", "change_pct": 110.3, "perf_week_pct": 213.16, "perf_month_pct": 490.79}, {"ticker": "AREC", "company": "American Resources Corporation", "sector": "Basic Materials", "industry": "Coking Coal", "market_cap": "576.18M", "change_pct": 36.75, "perf_week_pct": 75.06, "perf_month_pct": 177.96}, {"ticker": "CRML", "company": "Critical Metals Corp", "sector": "Basic Materials", "industry": "Other Industrial Metals & Mining", "market_cap": "3.20B", "change_pct": 28.74, "perf_week_pct": 199.1, "perf_month_pct": 347.98}]}}