{"status": "success", "message": "small nasdaq success, small nyse success, mid nasdaq success, mid nyse success", "change_pct": {"best3": [{"ticker": "FEIM", "company": "Frequency Electronics, Inc", "sector": "Technology", "industry": "Communication Equipment", "market_cap": "452.86M", "change_pct": 28.81, "perf_week_pct": 48.31, "perf_month_pct": 58.75}, {"ticker": "VFF", "company": "Village Farms International Inc", "sector": "Consumer Defensive", "industry": "Farm Products", "market_cap": "471.32M", "change_pct": 17.58, "perf_week_pct": 21.79, "perf_month_pct": 16.57}, {"ticker": "CRON", "company": "Cronos Group Inc", "sector": "Healthcare", "industry": "Drug Manufacturers - Specialty & Generic", "market_cap": "1.25B", "change_pct": 14.74, "perf_week_pct": 31.33, "perf_month_pct": 28.74}]}}