{"status": "success", "message": "small nasdaq success, small nyse success, mid nasdaq success, mid nyse success", "change_pct": {"best3": [{"ticker": "WSHP", "company": "WeShop Holdings Ltd", "sector": "Communication Services", "industry": "Internet Content & Information", "market_cap": "4.66B", "change_pct": 506.06, "perf_week_pct": null, "perf_month_pct": null}, {"ticker": "NUVB", "company": "Nuvation Bio Inc", "sector": "Healthcare", "industry": "Biotechnology", "market_cap": "2.46B", "change_pct": 48.96, "perf_week_pct": 45.03, "perf_month_pct": 69.83}, {"ticker": "FULC", "company": "Fulcrum Therapeutics Inc", "sector": "Healthcare", "industry": "Biotechnology", "market_cap": "622.90M", "change_pct": 18.29, "perf_week_pct": 37.68, "perf_month_pct": 18.66}]}}