{"status": "success", "message": "small nasdaq success, small nyse success, mid nasdaq success, mid nyse success", "aggregates": {"by_sector": {"Consumer Cyclical": {"change_pct_min": 3.87, "change_pct_max": 3.87, "change_pct_mean_pos": 3.87, "change_pct_mean_neg": null, "change_pct_count_pos": 1, "change_pct_count_neg": 0}, "Consumer Defensive": {"change_pct_min": -0.37, "change_pct_max": 24.38, "change_pct_mean_pos": 13.72, "change_pct_mean_neg": -0.37, "change_pct_count_pos": 2, "change_pct_count_neg": 1}, "Energy": {"change_pct_min": 3.64, "change_pct_max": 4.39, "change_pct_mean_pos": 4.01, "change_pct_mean_neg": null, "change_pct_count_pos": 2, "change_pct_count_neg": 0}, "Financial": {"change_pct_min": 0.5, "change_pct_max": 7.32, "change_pct_mean_pos": 3.62, "change_pct_mean_neg": null, "change_pct_count_pos": 7, "change_pct_count_neg": 0}, "Healthcare": {"change_pct_min": 0.57, "change_pct_max": 14.03, "change_pct_mean_pos": 6.41, "change_pct_mean_neg": null, "change_pct_count_pos": 20, "change_pct_count_neg": 0}, "Industrials": {"change_pct_min": 28.22, "change_pct_max": 28.22, "change_pct_mean_pos": 28.22, "change_pct_mean_neg": null, "change_pct_count_pos": 1, "change_pct_count_neg": 0}, "Real Estate": {"change_pct_min": 2.8, "change_pct_max": 10.34, "change_pct_mean_pos": 5.86, "change_pct_mean_neg": null, "change_pct_count_pos": 3, "change_pct_count_neg": 0}, "Technology": {"change_pct_min": 2.54, "change_pct_max": 10.26, "change_pct_mean_pos": 5.92, "change_pct_mean_neg": null, "change_pct_count_pos": 3, "change_pct_count_neg": 0}, "Utilities": {"change_pct_min": 0.07, "change_pct_max": 7.06, "change_pct_mean_pos": 1.99, "change_pct_mean_neg": null, "change_pct_count_pos": 5, "change_pct_count_neg": 0}}}}