{"status": "success", "message": "small nasdaq success, small nyse success, mid nasdaq success, mid nyse success", "change_pct": {"worst3": [{"ticker": "INV", "company": "Innventure inc", "sector": "Financial", "industry": "Asset Management", "market_cap": "312.36M", "change_pct": -13.04, "perf_week_pct": 18.2, "perf_month_pct": 96.08}, {"ticker": "MLTX", "company": "MoonLake Immunotherapeutics", "sector": "Healthcare", "industry": "Biotechnology", "market_cap": "945.70M", "change_pct": -3.5, "perf_week_pct": 4.58, "perf_month_pct": 35.07}, {"ticker": "JACK", "company": "Jack In The Box, Inc", "sector": "Consumer Cyclical", "industry": "Restaurants", "market_cap": "365.09M", "change_pct": -1.98, "perf_week_pct": 14.93, "perf_month_pct": 26.44}]}}